codoc/__init__.py
codoc/domain/__init__.py
codoc/domain/helpers.py
codoc/domain/model.py
codoc/entrypoints/__init__.py
codoc/entrypoints/cli.py
codoc/service/__init__.py
codoc/service/dependency_correcting.py
codoc/service/graph.py
codoc/service/object_unpacker.py
codoc/service/export/__init__.py
codoc/service/export/codoc_api.py
codoc/service/export/codoc_view.py
codoc/service/filters/__init__.py
codoc/service/filters/children_based.py
codoc/service/filters/class_diagram.py
codoc/service/filters/depth_based.py
codoc/service/filters/external_exclusion.py
codoc/service/filters/helpers.py
codoc/service/filters/high_order_filter.py
codoc/service/filters/regex_based.py
codoc/service/filters/type_exclusion_filter.py
codoc/service/filters/types.py
codoc/service/finder/__init__.py
codoc/service/finder/config.py
codoc/service/finder/files.py
codoc/service/finder/views.py
codoc/service/parsing/__init__.py
codoc/service/parsing/dependency.py
codoc/service/parsing/identifier_extractor.py
codoc/service/parsing/node.py
codoc/service/parsing/regex_identifier_extractor.py
codoc/service/parsing/types.py
codoc/service/parsing/utils.py
codoc_python-1.0.0.0.dist-info/METADATA
codoc_python-1.0.0.0.dist-info/WHEEL
codoc_python-1.0.0.0.dist-info/entry_points.txt
codoc_python-1.0.0.0.dist-info/top_level.txt
codoc_python-1.0.0.0.dist-info/RECORD
